Metadata-Version: 1.0
Name: all-distributions
Version: 1.0
Summary: Gaussian and binomial distributions
Home-page: UNKNOWN
Author: Laila Shahreen
Author-email: lailashahreen17@gmail.com
License: UNKNOWN
Platform: UNKNOWN
